MANIFEST.in
README.md
requirements.txt
setup.cfg
setup.py
NanoDB.egg-info/PKG-INFO
NanoDB.egg-info/SOURCES.txt
NanoDB.egg-info/dependency_links.txt
NanoDB.egg-info/requires.txt
NanoDB.egg-info/top_level.txt
libs/__init__.py
libs/client/__init__.py
libs/client/cli.py
libs/client/commandparser.py
libs/server/__init__.py
libs/server/interface.py
libs/server/loader.py
libs/server/nanocube.py
libs/server/node.py
libs/server/querybuilder.py
libs/server/serializer.py
libs/server/server.py
libs/server/timeserietable.py
nanodb.egg-info/SOURCES.txt
test/test_nanocube.py
test/test_querybuilder.py
test/test_serializer.py
test/test_timeserietable.py