Metadata-Version: 1.1
Name: nanodb
Version: 0.4.0
Summary: In memory database for geolocated and temporal data
Home-page: https://github.com/pmdartus/NanoCube
Author: Pierre-Marie Dartus
Author-email: dartus.pierremarie@gmail.com
License: Apache License 2.0
Download-URL: https://github.com/pmdartus/NanoCube/tarball/v0.4
Platform: UNKNOWN
Classifier: Development Status :: 3 - Alpha
Classifier: Intended Audience :: Developers
Classifier: Topic :: Database :: Database Engines/Servers
Classifier: License :: OSI Approved :: Apache Software License
Classifier: Programming Language :: Python :: 2.7
